eidos_sdk/__init__.py
eidos_sdk/agent/__init__.py
eidos_sdk/agent/agent.py
eidos_sdk/agent/doc_manager/__init__.py
eidos_sdk/agent/doc_manager/document_manager.py
eidos_sdk/agent/doc_manager/loaders/__init__.py
eidos_sdk/agent/doc_manager/loaders/base_loader.py
eidos_sdk/agent/doc_manager/loaders/filesystem_loader.py
eidos_sdk/agent/doc_manager/parsers/__init__.py
eidos_sdk/agent/doc_manager/parsers/auto_parser.py
eidos_sdk/agent/doc_manager/parsers/base_parser.py
eidos_sdk/agent/doc_manager/parsers/code_ast_parsers/__init__.py
eidos_sdk/agent/doc_manager/parsers/code_ast_parsers/base_ast_generator.py
eidos_sdk/agent/doc_manager/parsers/code_ast_parsers/cobol.py
eidos_sdk/agent/doc_manager/parsers/code_ast_parsers/javascript.py
eidos_sdk/agent/doc_manager/parsers/code_ast_parsers/programing_language_parser.py
eidos_sdk/agent/doc_manager/parsers/code_ast_parsers/python.py
eidos_sdk/agent/doc_manager/parsers/ms_word_parser.py
eidos_sdk/agent/doc_manager/parsers/pdf_parsers.py
eidos_sdk/agent/doc_manager/parsers/text_parsers.py
eidos_sdk/agent/doc_manager/transformer/__init__.py
eidos_sdk/agent/doc_manager/transformer/auto_transformer.py
eidos_sdk/agent/doc_manager/transformer/document_transformer.py
eidos_sdk/agent/doc_manager/transformer/text_splitters.py
eidos_sdk/agent/generic_agent.py
eidos_sdk/agent/retriever_agent/__init__.py
eidos_sdk/agent/retriever_agent/document_reranker.py
eidos_sdk/agent/retriever_agent/hyde_question_transformer.py
eidos_sdk/agent/retriever_agent/multi_question_transformer.py
eidos_sdk/agent/retriever_agent/question_transformer.py
eidos_sdk/agent/retriever_agent/retriever_agent.py
eidos_sdk/agent/tot_agent/__init__.py
eidos_sdk/agent/tot_agent/checker.py
eidos_sdk/agent/tot_agent/controller.py
eidos_sdk/agent/tot_agent/memory.py
eidos_sdk/agent/tot_agent/prompts.py
eidos_sdk/agent/tot_agent/thought.py
eidos_sdk/agent/tot_agent/thought_generators.py
eidos_sdk/agent/tot_agent/tot_agent.py
eidos_sdk/agent_os.py
eidos_sdk/bin/__init__.py
eidos_sdk-0.1.12.dist-info/METADATA
eidos_sdk-0.1.12.dist-info/WHEEL
eidos_sdk-0.1.12.dist-info/entry_points.txt
eidos_sdk-0.1.12.dist-info/RECORD
