Metadata-Version: 2.1
Name: eidos-sdk
Version: 0.1.12
Summary: 
Author: Luke Lalor
Author-email: lukehlalor@gmail.com
Requires-Python: >=3.11,<3.12
Classifier: Programming Language :: Python :: 3
Classifier: Programming Language :: Python :: 3.11
Requires-Dist: aiohttp (>=3.9.1,<4.0.0)
Requires-Dist: chromadb (>=0.4.18,<0.5.0)
Requires-Dist: esprima (>=4.0.1,<5.0.0)
Requires-Dist: fastapi (>=0.104.1,<0.105.0)
Requires-Dist: filetype (>=1.2.0,<2.0.0)
Requires-Dist: httpx (>=0.25.1,<0.26.0)
Requires-Dist: jinja2 (>=3.1.2,<4.0.0)
Requires-Dist: jsonref (>=1.1.0,<2.0.0)
Requires-Dist: jsonschema (>=4.19.2,<5.0.0)
Requires-Dist: lxml (>=4.9.3,<5.0.0)
Requires-Dist: motor (>=3.3.1,<4.0.0)
Requires-Dist: numpy (>=1.26.2,<2.0.0)
Requires-Dist: openai (>=1.2.4,<2.0.0)
Requires-Dist: pillow (>=10.1.0,<11.0.0)
Requires-Dist: pypdf (>=3.17.1,<4.0.0)
Requires-Dist: pytest-json-report (>=1.5.0,<2.0.0)
Requires-Dist: python-docx (>=1.1.0,<2.0.0)
Requires-Dist: python-dotenv (>=1.0.0,<2.0.0)
Requires-Dist: python-multipart (>=0.0.6,<0.0.7)
Requires-Dist: pyyaml (>=6.0.1,<7.0.0)
Requires-Dist: spacy (>=3.7.2,<4.0.0)
Requires-Dist: tiktoken (>=0.5.1,<0.6.0)
Requires-Dist: unstructured (>=0.11.2,<0.12.0)
Requires-Dist: uvicorn (>=0.24.0.post1,<0.25.0)
Requires-Dist: watchdog (>=3.0.0,<4.0.0)
